sync_mutidata_3/mutidata_3.v
//==================================================================================================
//  Filename      : mutidata_3.v
//  Created On    : 2022-10-05 16:20:53
//  Last Modified : 2022-10-05 17:16:56
//  Revision      : 
//  Author        : Jason
//  Company       : HKUST
//  Email         : Jasonxx075@gmail.com
//
//  Description   : 部分握手信号，脉冲响应
//
//
//==================================================================================================
module mutidata3 (clk_i, rst_i,in_pulse,din,
    clk_o,rst_o,out_pulse,dout);

    input clk_i;
    input rst_i;
    input [7:0] din;
    input rst_o;
    input clk_o;
    input in_pulse;
    output reg [7:0] dout;
    output  reg out_pulse;

    reg [7:0] din_temp;
    reg in_request;//电平信号，跨时钟传输

always @(posedge clk_i) begin
    if (rst_i == 0) begin
        // reset
        in_request <= 0;
    end
    else if (in_pulse == 1) begin
        in_request <= 1;
    end
end

always @(posedge clk_i) begin
    if (rst_i == 0) begin
        // reset
        din_temp = 8'b0;
    end
    else if (in_pulse== 1) begin
        din_temp <= din;
    end
end

//in_request信号同步到clk out
reg out_vld_q1;
reg out_vld_q2;
always @ (posedge clk_o) begin
    if(rst_o == 0)begin
        out_vld_q1 <= 0;
        out_vld_q2 <= 0;
    end
    else begin
        out_vld_q1 <= in_request;
        out_vld_q2 <= out_vld_q1;
        out_pulse <= out_vld_q1 && ~out_vld_q2;
    end
end

//处理out_vld信号,生成输出
always @(posedge clk_o) begin
    if (rst_o == 0) begin
        // reset
        dout <= 0;
    end
    else if (out_pulse == 1) begin
        dout <= din_temp;      
    end
end

reg in_vld_q1;
reg in_vld_q2;
//将out_vld信号同步到clk_in
always @(posedge clk_i) begin
    if (rst_i == 0) begin
        // reset
        in_vld_q1 <= 1'b0;
        in_vld_q2 <= 1'b0;
    end
    else begin
        in_vld_q1 <= out_vld_q2;
        in_vld_q2 <= in_vld_q1;
    end
end

//拉低in_vld信号
always @(posedge clk_i) begin
    if (rst_i == 0) begin
        // reset
        in_request <= 1'b0;
    end
    else if (in_vld_q2 == 1) begin
        in_request <= 1'b0;
    end
end

endmodule

sync_mutidata_3/tb_mutidata3.sv
`include "mutidata_3.v"
`timescale 1ns/1ps

module tb_mutidata3 (); /* this is automatically generated */

	// clock
	logic clk1;
	initial begin
		clk1 = '0;
		forever #(5) clk1 = ~clk1;
	end
	logic clk2;
	initial begin
		clk2 = '0;
		forever #(0.5) clk2 = ~clk2;
	end

	// (*NOTE*) replace reset, clock, others

	logic       rst_i;
	logic       in_pulse;
	logic [7:0] din;
	logic       rst_o;
	logic       out_pulse;
	logic [7:0] dout;

	mutidata3 inst_mutidata3
		(
			.clk_i     (clk1),
			.rst_i     (rst_i),
			.in_pulse  (in_pulse),
			.din       (din),
			.clk_o     (clk2),
			.rst_o     (rst_o),
			.out_pulse (out_pulse),
			.dout      (dout)
		);

	task init();
		rst_i    <= '0;
		in_pulse <= '0;
		din      <= '0;
		rst_o    <= '0;
	endtask

	task genpulse();
		in_pulse <= 1'b1;
		repeat(1)@(posedge clk2);
		in_pulse <= 1'b0;
	endtask

	initial begin
		// do something

		init();
		repeat(2)@(posedge clk2);
		rst_o <= '1;
		rst_i <= '1;

		repeat(10)@(posedge clk2);
		din <= 8'd5;
		genpulse();

		repeat(10)@(posedge clk2);
		din <= 8'd11;
		genpulse();

		repeat(10)@(posedge clk2);
		din <= 8'd4;
		genpulse();

		repeat(10)@(posedge clk2);
		din <= 8'd8;
		genpulse();

		repeat(10)@(posedge clk2);
		din <= 8'd14;
		genpulse();

		repeat(20)@(posedge clk1);
		$finish;
	end

	// dump wave
	initial
	begin            
	    $dumpfile("wave.vcd");        //生成的vcd文件名称
	    $dumpvars(0, tb_mutidata3);    //tb模块名称
	end

endmodule

sync_mutidata_3/wave.vcd
$date
	Wed Oct 05 17:33:44 2022
$end
$version
	Icarus Verilog
$end
$timescale
	1ps
$end
$scope module tb_mutidata3 $end
$var wire 1 ! out_pulse $end
$var wire 8 " dout [7:0] $end
$var reg 1 # clk1 $end
$var reg 1 $ clk2 $end
$var reg 8 % din [7:0] $end
$var reg 1 & in_pulse $end
$var reg 1 ' rst_i $end
$var reg 1 ( rst_o $end
$scope module inst_mutidata3 $end
$var wire 1 # clk_i $end
$var wire 1 $ clk_o $end
$var wire 8 ) din [7:0] $end
$var wire 1 & in_pulse $end
$var wire 1 ' rst_i $end
$var wire 1 ( rst_o $end
$var reg 8 * din_temp [7:0] $end
$var reg 8 + dout [7:0] $end
$var reg 1 , in_request $end
$var reg 1 - in_vld_q1 $end
$var reg 1 . in_vld_q2 $end
$var reg 1 ! out_pulse $end
$var reg 1 / out_vld_q1 $end
$var reg 1 0 out_vld_q2 $end
$upscope $end
$scope task genpulse $end
$upscope $end
$scope task init $end
$upscope $end
$upscope $end
$enddefinitions $end
$comment Show the parameter values. $end
$dumpall
$end
#0
$dumpvars
x0
x/
x.
x-
x,
bx +
bx *
b0 )
0(
0'
0&
b0 %
0$
0#
bx "
x!
$end
#500
00
0/
b0 "
b0 +
1$
#1000
0$
#1500
1'
1(
1$
#2000
0$
#2500
0!
x/
1$
#3000
0$
#3500
x!
x0
1$
#4000
0$
#4500
1$
#5000
0$
1#
#5500
1$
#6000
0$
#6500
1$
#7000
0$
#7500
1$
#8000
0$
#8500
1$
#9000
0$
#9500
1$
#10000
0$
0#
#10500
1$
#11000
0$
#11500
1&
b101 %
b101 )
1$
#12000
0$
#12500
0&
1$
#13000
0$
#13500
1$
#14000
0$
#14500
1$
#15000
0$
1#
#15500
1$
#16000
0$
#16500
1$
#17000
0$
#17500
1$
#18000
0$
#18500
1$
#19000
0$
#19500
1$
#20000
0$
0#
#20500
1$
#21000
0$
#21500
1$
#22000
0$
#22500
1&
b1011 %
b1011 )
1$
#23000
0$
#23500
0&
1$
#24000
0$
#24500
1$
#25000
0$
1#
#25500
1$
#26000
0$
#26500
1$
#27000
0$
#27500
1$
#28000
0$
#28500
1$
#29000
0$
#29500
1$
#30000
0$
0#
#30500
1$
#31000
0$
#31500
1$
#32000
0$
#32500
1$
#33000
0$
#33500
1&
b100 %
b100 )
1$
#34000
0$
#34500
0&
1$
#35000
0$
1#
#35500
1$
#36000
0$
#36500
1$
#37000
0$
#37500
1$
#38000
0$
#38500
1$
#39000
0$
#39500
1$
#40000
0$
0#
#40500
1$
#41000
0$
#41500
1$
#42000
0$
#42500
1$
#43000
0$
#43500
1$
#44000
0$
#44500
1&
b1000 %
b1000 )
1$
#45000
1,
b1000 *
0$
1#
#45500
1/
0&
1$
#46000
0$
#46500
10
1$
#47000
0$
#47500
0!
1$
#48000
0$
#48500
1$
#49000
0$
#49500
1$
#50000
0$
0#
#50500
1$
#51000
0$
#51500
1$
#52000
0$
#52500
1$
#53000
0$
#53500
1$
#54000
0$
#54500
1$
#55000
1-
0$
1#
#55500
1&
b1110 %
b1110 )
1$
#56000
0$
#56500
0&
1$
#57000
0$
#57500
1$
#58000
0$
#58500
1$
#59000
0$
#59500
1$
#60000
0$
0#
#60500
1$
#61000
0$
#61500
1$
#62000
0$
#62500
1$
#63000
0$
#63500
1$
#64000
0$
#64500
1$
#65000
1.
0$
1#
#65500
1$
#66000
0$
#66500
1$
#67000
0$
#67500
1$
#68000
0$
#68500
1$
#69000
0$
#69500
1$
#70000
0$
0#
#70500
1$
#71000
0$
#71500
1$
#72000
0$
#72500
1$
#73000
0$
#73500
1$
#74000
0$
#74500
1$
#75000
0,
0$
1#
#75500
0/
1$
#76000
0$
#76500
00
1$
#77000
0$
#77500
1$
#78000
0$
#78500
1$
#79000
0$
#79500
1$
#80000
0$
0#
#80500
1$
#81000
0$
#81500
1$
#82000
0$
#82500
1$
#83000
0$
#83500
1$
#84000
0$
#84500
1$
#85000
0-
0$
1#
#85500
1$
#86000
0$
#86500
1$
#87000
0$
#87500
1$
#88000
0$
#88500
1$
#89000
0$
#89500
1$
#90000
0$
0#
#90500
1$
#91000
0$
#91500
1$
#92000
0$
#92500
1$
#93000
0$
#93500
1$
#94000
0$
#94500
1$
#95000
0.
0$
1#
