sync_mutidata_2/mutidata_2.v
//==================================================================================================
//  Filename      : mutidata_2.v
//  Created On    : 2022-10-03 12:10:58
//  Last Modified : 2022-10-03 21:00:45
//  Revision      : 
//  Author        : Jason
//  Company       : HKUST
//  Email         : Jasonxx075@gmail.com
//
//  Description   : 部分握手信号，r_ack脉冲响应
//
//==================================================================================================
module mutidata (clk_i, rst_i,in_vld,din,
    clk_o,rst_o,r_ack,dout);

    input clk_i;
    input rst_i;
    input [7:0] din;
    //input in_ack;
    input rst_o;
    input clk_o;
    output reg in_vld;
    output reg [7:0] dout;
    output reg r_ack; //r_ack
    //output  reg out_vld;

    reg [7:0] din_temp;
    reg flag;
//in_acknowledge信号，这是一个跨时钟域信号单比特脉冲信号
//检测数据变化的这个脉冲信号
always @(din) begin
    if (rst_i == 0) begin
        // reset
        in_vld <= 0;
        flag <= 0;
    end
    else 
        flag <= 1;
end

always @(posedge clk_i) begin
    if (rst_i == 0) begin
        // reset
        in_vld = 0;
    end
    else if (flag == 1) begin
        in_vld <= 1;
        flag <= 0;
    end
end

always @(posedge clk_i) begin
    if (rst_i == 0) begin
        // reset
        din_temp = 8'b0;
    end
    else if (in_vld == 1) begin
        din_temp <= din;
    end
end

//in_vld信号同步到clk out
reg out_vld_q1;
reg out_vld_q2;
reg out_vld_q3;
reg out_vld;
always @ (posedge clk_o) begin
    if(rst_o == 0)begin
        out_vld_q1 <= 0;
        out_vld_q2 <= 0;
    end
    else begin
        out_vld_q1 <= in_vld;
        out_vld_q2 <= out_vld_q1;
        r_ack <= ~out_vld_q2 && out_vld_q1;
    end
end

//处理out_vld信号,生成输出
always @(posedge clk_o) begin
    if (rst_o == 0) begin
        // reset
        dout <= 0;
    end
    else if (r_ack == 1) begin
        dout <= din_temp;      
    end
end

//生成r_ack_level信号
reg r_ack_level;
always @(posedge clk_o) begin
	if (rst_o == 0) begin
		// reset
		r_ack_level <= 0;
	end
	else if ((r_ack == 1) && (out_vld_q2 == 1)) begin
		r_ack_level <= ~r_ack_level;
	end
end

reg in_vld_q1;
reg in_vld_q2;
//reg in_vld_q3;
reg in_ack_pluse;
//将r_ack_level信号同步到clk_in
always @(posedge clk_i) begin
    if (rst_i == 0) begin
        // reset
        in_vld_q1 <= 1'b0;
        //in_vld_q2 <= 1'b0;
    end
    else  begin
    	in_vld_q1 <= out_vld_q2;
    	in_vld_q2 <= in_vld_q1;
    	in_ack_pluse <= ~in_vld_q2 && in_vld_q1;
    end
end

//拉低in_vld信号
always @(posedge clk_i) begin
    if (rst_i == 0) begin
        // reset
        in_vld <= 1'b0;
    end
    else if ((in_ack_pluse == 1) && (flag ==0))begin
        in_vld <= 1'b0;
    end
end

endmodule

sync_mutidata_2/tb_mutidata.sv
`include "mutidata_2.v"
`timescale 1ns/1ps

module tb_mutidata (); /* this is automatically generated */

	// clock
	logic clk1;
	initial begin
		clk1 = '0;
		forever #(1) clk1 = ~clk1;
	end
	logic clk2;
	initial begin
		clk2 = '0;
		forever #(0.5) clk2 = ~clk2;
	end

	// (*NOTE*) replace reset, clock, others

	logic       rst_i;
	logic       in_vld;
	logic [7:0] din;
	logic       rst_o;
	logic       r_ack;
	logic [7:0] dout;

	mutidata inst_mutidata
		(
			.clk_i  (clk1),
			.rst_i  (rst_i),
			.in_vld (in_vld),
			.din    (din),
			.clk_o  (clk2),
			.rst_o  (rst_o),
			.r_ack  (r_ack),
			.dout   (dout)
		);

	task init();
		rst_i <= '0;
		din   <= '0;
		rst_o <= '0;
	endtask

	initial begin
		// do something

		init();
		repeat(2)@(posedge clk1);
		rst_o <= 1;
		rst_i <= 1;
		repeat(5)@(posedge clk1);
		din <= 8'd4;
		repeat(5)@(posedge clk1);
		din <= 8'd10;
		repeat(5)@(posedge clk1);
		din <= 8'd5;	
		repeat(5)@(posedge clk1);
		din <= 8'd8;
		repeat(100)@(posedge clk1);	
		$finish;
	end

	// dump wave
	initial
	begin            
	    $dumpfile("wave.vcd");        //生成的vcd文件名称
	    $dumpvars(0, tb_mutidata);    //tb模块名称
	end

endmodule

sync_mutidata_2/wave.vcd
$date
	Mon Oct 03 21:01:02 2022
$end
$version
	Icarus Verilog
$end
$timescale
	1ps
$end
$scope module tb_mutidata $end
$var wire 1 ! r_ack $end
$var wire 1 " in_vld $end
$var wire 8 # dout [7:0] $end
$var reg 1 $ clk1 $end
$var reg 1 % clk2 $end
$var reg 8 & din [7:0] $end
$var reg 1 ' rst_i $end
$var reg 1 ( rst_o $end
$scope module inst_mutidata $end
$var wire 1 $ clk_i $end
$var wire 1 % clk_o $end
$var wire 8 ) din [7:0] $end
$var wire 1 ' rst_i $end
$var wire 1 ( rst_o $end
$var reg 8 * din_temp [7:0] $end
$var reg 8 + dout [7:0] $end
$var reg 1 , flag $end
$var reg 1 - in_ack_pluse $end
$var reg 1 " in_vld $end
$var reg 1 . in_vld_q1 $end
$var reg 1 / in_vld_q2 $end
$var reg 1 0 out_vld_q1 $end
$var reg 1 1 out_vld_q2 $end
$var reg 1 ! r_ack $end
$var reg 1 2 r_ack_level $end
$upscope $end
$scope task init $end
$upscope $end
$upscope $end
$enddefinitions $end
$comment Show the parameter values. $end
$dumpall
$end
#0
$dumpvars
x2
x1
x0
x/
x.
x-
0,
bx +
bx *
b0 )
0(
0'
b0 &
0%
0$
bx #
0"
x!
$end
#500
01
00
b0 #
b0 +
02
1%
#1000
0.
b0 *
0%
1$
#1500
1%
#2000
0%
0$
#2500
1%
#3000
1'
1(
0%
1$
#3500
0!
1%
#4000
0%
0$
#4500
1%
#5000
0-
0/
0%
1$
#5500
1%
#6000
0%
0$
#6500
1%
#7000
0%
1$
#7500
1%
#8000
0%
0$
#8500
1%
#9000
0%
1$
#9500
1%
#10000
0%
0$
#10500
1%
#11000
0%
1$
#11500
1%
#12000
0%
0$
#12500
1%
#13000
1,
b100 &
b100 )
0%
1$
#13500
1%
#14000
0%
0$
#14500
1%
#15000
0,
1"
0%
1$
#15500
10
1%
#16000
0%
0$
#16500
1!
11
1%
#17000
b100 *
1.
0%
1$
#17500
12
b100 #
b100 +
0!
1%
#18000
0%
0$
#18500
1%
#19000
1-
1/
0%
1$
#19500
1%
#20000
0%
0$
#20500
1%
#21000
0-
0"
0%
1$
#21500
00
1%
#22000
0%
0$
#22500
01
1%
#23000
1,
b1010 &
b1010 )
0.
0%
1$
#23500
1%
#24000
0%
0$
#24500
1%
#25000
0,
1"
0/
0%
1$
#25500
10
1%
#26000
0%
0$
#26500
1!
11
1%
#27000
1.
b1010 *
0%
1$
#27500
02
b1010 #
b1010 +
0!
1%
#28000
0%
0$
#28500
1%
#29000
1-
1/
0%
1$
#29500
1%
#30000
0%
0$
#30500
1%
#31000
0"
0-
0%
1$
#31500
00
1%
#32000
0%
0$
#32500
01
1%
#33000
1,
0.
b101 &
b101 )
0%
1$
#33500
1%
#34000
0%
0$
#34500
1%
#35000
0/
0,
1"
0%
1$
#35500
10
1%
#36000
0%
0$
#36500
1!
11
1%
#37000
b101 *
1.
0%
1$
#37500
12
b101 #
b101 +
0!
1%
#38000
0%
0$
#38500
1%
#39000
1-
1/
0%
1$
#39500
1%
#40000
0%
0$
#40500
1%
#41000
0-
0"
0%
1$
#41500
00
1%
#42000
0%
0$
#42500
01
1%
#43000
1,
b1000 &
b1000 )
0.
0%
1$
#43500
1%
#44000
0%
0$
#44500
1%
#45000
0,
1"
0/
0%
1$
#45500
10
1%
#46000
0%
0$
#46500
1!
11
1%
#47000
1.
b1000 *
0%
1$
#47500
02
b1000 #
b1000 +
0!
1%
#48000
0%
0$
#48500
1%
#49000
1-
1/
0%
1$
#49500
1%
#50000
0%
0$
#50500
1%
#51000
0"
0-
0%
1$
#51500
00
1%
#52000
0%
0$
#52500
01
1%
#53000
0.
0%
1$
#53500
1%
#54000
0%
0$
#54500
1%
#55000
0/
0%
1$
